readms/__init__.py
readms/cli.py
readms-0.1.0.dist-info/LICENSE
readms-0.1.0.dist-info/METADATA
readms-0.1.0.dist-info/WHEEL
readms-0.1.0.dist-info/entry_points.txt
readms-0.1.0.dist-info/top_level.txt
readms-0.1.0.dist-info/RECORD
