Metadata-Version: 2.1
Name: readms
Version: 0.1.0
Summary: Get the last chapter OUT and be notified !!!
Home-page: https://github.com/nekomamoushi/readms
Author: Jerome Pradier
Author-email: jerome.pradier@gmail.com
License: MIT
Keywords: packaging setuptools development
Platform: UNKNOWN
Classifier: Development Status :: 4 - Beta
Classifier: Intended Audience :: Developers
Classifier: Topic :: Software Development :: Build Tools
Classifier: License :: OSI Approved :: MIT License
Classifier: Programming Language :: Python :: 2
Classifier: Programming Language :: Python :: 2.7
Classifier: Programming Language :: Python :: 3
Classifier: Programming Language :: Python :: 3.5
Classifier: Programming Language :: Python :: 3.6
Classifier: Programming Language :: Python :: 3.7
